Metadata-Version: 2.1
Name: fairdetect-muo
Version: 0.6
Summary: Library to identify bias in pre-trained models!
Home-page: https://github.com/manoelgadi/fairdetect
Author: Prof. Manoel Gadi
Author-email: mfalonso@faculty.ie.edu
License: MIT
Platform: UNKNOWN
